soltrannet/__init__.py
soltrannet/command_line.py
soltrannet/data_utils.py
soltrannet/predict.py
soltrannet/soltrannet_aqsol_trained.weights
soltrannet/transformer.py
soltrannet/tests/__init__.py
soltrannet/tests/test_commandline.py
soltrannet/tests/test_loading_smiles.py
soltrannet/tests/test_predictions.py
soltrannet/tests/test_torchgpu.py
soltrannet/tests/test_warnings.py
soltrannet-1.0.0.dist-info/LICENSE.txt
soltrannet-1.0.0.dist-info/METADATA
soltrannet-1.0.0.dist-info/WHEEL
soltrannet-1.0.0.dist-info/entry_points.txt
soltrannet-1.0.0.dist-info/top_level.txt
soltrannet-1.0.0.dist-info/RECORD
